fds/__init__.py
fds/sdk/__init__.py
fds/sdk/AxiomaFixedIncomeOptimizer/__init__.py
fds/sdk/AxiomaFixedIncomeOptimizer/api_client.py
fds/sdk/AxiomaFixedIncomeOptimizer/configuration.py
fds/sdk/AxiomaFixedIncomeOptimizer/exceptions.py
fds/sdk/AxiomaFixedIncomeOptimizer/model_utils.py
fds/sdk/AxiomaFixedIncomeOptimizer/rest.py
fds/sdk/AxiomaFixedIncomeOptimizer/api/__init__.py
fds/sdk/AxiomaFixedIncomeOptimizer/api/afi_optimizer_api.py
fds/sdk/AxiomaFixedIncomeOptimizer/api/strategy_documents_api.py
fds/sdk/AxiomaFixedIncomeOptimizer/apis/__init__.py
fds/sdk/AxiomaFixedIncomeOptimizer/model/__init__.py
fds/sdk/AxiomaFixedIncomeOptimizer/model/afi_optimization_parameters.py
fds/sdk/AxiomaFixedIncomeOptimizer/model/afi_optimization_parameters_root.py
fds/sdk/AxiomaFixedIncomeOptimizer/model/afi_optimizer_strategy.py
fds/sdk/AxiomaFixedIncomeOptimizer/model/afi_optimizer_strategy_overrides.py
fds/sdk/AxiomaFixedIncomeOptimizer/model/calculation_info.py
fds/sdk/AxiomaFixedIncomeOptimizer/model/calculation_info_root.py
fds/sdk/AxiomaFixedIncomeOptimizer/model/client_error_response.py
fds/sdk/AxiomaFixedIncomeOptimizer/model/document_directories.py
fds/sdk/AxiomaFixedIncomeOptimizer/model/document_directories_root.py
fds/sdk/AxiomaFixedIncomeOptimizer/model/error.py
fds/sdk/AxiomaFixedIncomeOptimizer/model/error_source.py
fds/sdk/AxiomaFixedIncomeOptimizer/model/object_root.py
fds/sdk/AxiomaFixedIncomeOptimizer/model/optimal_portfolio.py
fds/sdk/AxiomaFixedIncomeOptimizer/model/optimization.py
fds/sdk/AxiomaFixedIncomeOptimizer/model/optimizer_account.py
fds/sdk/AxiomaFixedIncomeOptimizer/model/optimizer_account_overrides.py
fds/sdk/AxiomaFixedIncomeOptimizer/model/optimizer_optimal_holdings.py
fds/sdk/AxiomaFixedIncomeOptimizer/model/optimizer_output_types.py
fds/sdk/AxiomaFixedIncomeOptimizer/model/optimizer_trades_list.py
fds/sdk/AxiomaFixedIncomeOptimizer/models/__init__.py
fds.sdk.AxiomaFixedIncomeOptimizer-0.21.15.dist-info/LICENSE
fds.sdk.AxiomaFixedIncomeOptimizer-0.21.15.dist-info/METADATA
fds.sdk.AxiomaFixedIncomeOptimizer-0.21.15.dist-info/WHEEL
fds.sdk.AxiomaFixedIncomeOptimizer-0.21.15.dist-info/top_level.txt
fds.sdk.AxiomaFixedIncomeOptimizer-0.21.15.dist-info/RECORD
